wait_for_docker/__init__.py
wait_for_docker/main.py
wait_for_docker-0.3.0.dist-info/METADATA
wait_for_docker-0.3.0.dist-info/WHEEL
wait_for_docker-0.3.0.dist-info/entry_points.txt
wait_for_docker-0.3.0.dist-info/RECORD
